pycelium/__init__.py
pycelium/action.py
pycelium/agent.py
pycelium/cli.py
pycelium/containers.py
pycelium/definitions.py
pycelium/gathering.py
pycelium/grafana.py
pycelium/installer.py
pycelium/iptables.py
pycelium/modem.py
pycelium/netplan.py
pycelium/network.py
pycelium/ntp.py
pycelium/packages.py
pycelium/pastor.py
pycelium/pawn.py
pycelium/pycelium.py
pycelium/rsync.py
pycelium/scanner.py
pycelium/service.py
pycelium/shell.py
pycelium/ssh.py
pycelium/watch.py
pycelium/wingdbstub.old.py
pycelium/wingdbstub.py
pycelium/wireguard.py
pycelium/data/logging.yaml
pycelium/tools/__init__.py
pycelium/tools/calls.py
pycelium/tools/colors.py
pycelium/tools/configurations.py
pycelium/tools/containers.py
pycelium/tools/helpers.py
pycelium/tools/inventory.py
pycelium/tools/logs.py
pycelium/tools/metrics.py
pycelium/tools/mixer.py
pycelium/tools/persistence.py
pycelium/tools/sequencers.py
pycelium/tools/templating.py
pycelium/tools/cli/__init__.py
pycelium/tools/cli/config.py
pycelium/tools/cli/get.py
pycelium/tools/cli/inventory.py
pycelium/tools/cli/main.py
pycelium/tools/cli/run.py
pycelium-0.1.42.data/data/data/logging.yaml
pycelium-0.1.42.dist-info/AUTHORS.rst
pycelium-0.1.42.dist-info/LICENSE
pycelium-0.1.42.dist-info/METADATA
pycelium-0.1.42.dist-info/WHEEL
pycelium-0.1.42.dist-info/entry_points.txt
pycelium-0.1.42.dist-info/top_level.txt
pycelium-0.1.42.dist-info/RECORD
