Metadata-Version: 2.1
Name: pycelium
Version: 0.1.42
Summary: Python Mycelium Edge Swarm Network
Home-page: https://github.com/asteriogonzalez/pycelium
Author: Asterio Gonzalez
Author-email: asterio.gonzalez@gmail.com
License: BSD license
Keywords: pycelium
Platform: UNKNOWN
Classifier: Development Status :: 2 - Pre-Alpha
Classifier: Intended Audience :: Developers
Classifier: License :: OSI Approved :: BSD License
Classifier: Natural Language :: English
Classifier: Programming Language :: Python :: 3
Classifier: Programming Language :: Python :: 3.9
Classifier: Programming Language :: Python :: 3.10
Classifier: Programming Language :: Python :: 3.11
Requires-Python: >=3.9
License-File: LICENSE
License-File: AUTHORS.rst
Requires-Dist: Jinja2
Requires-Dist: PyYAML
Requires-Dist: arrow
Requires-Dist: asyncio-mqtt
Requires-Dist: asyncssh
Requires-Dist: click
Requires-Dist: codenamize
Requires-Dist: colorama
Requires-Dist: debug
Requires-Dist: glom
Requires-Dist: jmespath
Requires-Dist: numpy
Requires-Dist: paho-mqtt
Requires-Dist: pytest
Requires-Dist: python-dateutil
Requires-Dist: semver
Requires-Dist: setuptools
